bump_testclient/__init__.py
bump_testclient/__main__.py
bump_testclient/command.py
bump_testclient/main.py
tests/__init__.py
tests/test_transformer.py
bump_testclient-0.3.0.dist-info/LICENSE
bump_testclient-0.3.0.dist-info/METADATA
bump_testclient-0.3.0.dist-info/WHEEL
bump_testclient-0.3.0.dist-info/entry_points.txt
bump_testclient-0.3.0.dist-info/top_level.txt
bump_testclient-0.3.0.dist-info/RECORD
