Metadata-Version: 2.1
Name: bump-testclient
Version: 0.3.0
Summary: Replace Starlette's TestClient from `requests` to `httpx`! 🎉
Home-page: https://github.com/Kludex/bump-testclient
Author: Marcelo Trylesinski
Author-email: marcelotryle@email.com
License: MIT
Project-URL: Twitter, https://twitter.com/marcelotryle
Platform: UNKNOWN
Classifier: License :: OSI Approved :: MIT License
Classifier: Intended Audience :: Developers
Classifier: Natural Language :: English
Classifier: Operating System :: OS Independent
Classifier: Programming Language :: Python :: 3 :: Only
Classifier: Programming Language :: Python :: 3
Classifier: Programming Language :: Python :: 3.7
Classifier: Programming Language :: Python :: 3.8
Classifier: Programming Language :: Python :: 3.9
Classifier: Programming Language :: Python :: 3.10
Requires-Python: >=3.7
License-File: LICENSE
Requires-Dist: packaging
Requires-Dist: libcst
Requires-Dist: typer
Provides-Extra: test
Requires-Dist: coverage[toml] (>=6.2) ; extra == 'test'
Requires-Dist: pytest (>=6.2.5) ; extra == 'test'
Requires-Dist: black ; extra == 'test'
Requires-Dist: flake8 ; extra == 'test'
Requires-Dist: isort ; extra == 'test'
